{"maximum_soil_moisture":150.0,"number_simulations":1000,"maximum_growth_rate":65.0,"supplement_price":0.5,"energy_for_bcs_milking":[-89.21238476063084,-83.48314904205822,-77.7539133234856,-72.02467760491297,-66.29544188634034,-60.56620616776773,-54.8369704491951,-49.10773473062248,-43.37849901204986,-37.64926329347724,-31.920027574904616,-26.190791856331987,-20.46155613775937,-14.732320419186742,-9.003084700614119,-3.2738489820414993,4.93314914729693,6.839680218716035,8.007430499960234,9.175180781204434,10.342931062448637,11.510681343692838,12.678431624937037,13.846181906181238,15.013932187425436,16.181682468669642,17.34943274991384,18.51718303115804,19.684933312402244,20.852683593646443,22.020433874890642,23.18818415613484,24.355934437379045,25.52368471862325,26.691434999867447,27.859185281111653,29.02693556235585,30.19468584360005,31.36243612484425,32.530186406088454,33.69793668733265,34.86568696857686,36.033437249821056,37.20118753106525,38.368937812309454,39.536688093553664,40.70443837479786,41.872188656042056,43.03993893728626,44.20768921853046,45.37543949977466,46.54318978101886],"pasture_energy_density":11.0,"niwa_data":[[{"evapotranspiration":3.4,"rainfall":15.8,"year":1,"week":1},{"evapotranspiration":3.8,"rainfall":31.9,"year":2,"week":1},{"evapotranspiration":3.8,"rainfall":62.8,"year":3,"week":1},{"evapotranspiration":4.2,"rainfall":32.167,"year":4,"week":1},{"evapotranspiration":4.0,"rainfall":11.633,"year":5,"week":1},{"evapotranspiration":4.1,"rainfall":9.733,"year":6,"week":1},{"evapotranspiration":2.1,"rainfall":78.2,"year":7,"week":1},{"evapotranspiration":3.0,"rainfall":39.933,"year":8,"week":1},{"evapotranspiration":4.7,"rainfall":30.3,"year":9,"week":1},{"evapotranspiration":3.8,"rainfall":91.267,"year":10,"week":1},{"evapotranspiration":3.6,"rainfall":127.7,"year":11,"week":1},{"evapotranspiration":3.0,"rainfall":174.5,"year":12,"week":1},{"evapotranspiration":3.2,"rainfall":45.933,"year":13,"week":1},{"evapotranspiration":3.6,"rainfall":136.333,"year":14,"week":1},{"evapotranspiration":4.5,"rainfall":0.933,"year":15,"week":1},{"evapotranspiration":3.8,"rainfall":178.1,"year":16,"week":1},{"evapotranspiration":3.9,"rainfall":10.967,"year":17,"week":1},{"evapotranspiration":5.4,"rainfall":18.6,"year":18,"week":1},{"evapotranspiration":3.5,"rainfall":44.4,"year":19,"week":1},{"evapotranspiration":3.7,"rainfall":29.867,"year":20,"week":1}],[{"evapotranspiration":4.5,"rainfall":0.0,"year":1,"week":2},{"evapotranspiration":4.8,"rainfall":0.267,"year":2,"week":2},{"evapotranspiration":5.7,"rainfall":11.533,"year":3,"week":2},{"evapotranspiration":5.4,"rainfall":16.9,"year":4,"week":2},{"evapotranspiration":5.5,"rainfall":23.7,"year":5,"week":2},{"evapotranspiration":4.0,"rainfall":55.667,"year":6,"week":2},{"evapotranspiration":4.4,"rainfall":13.167,"year":7,"week":2},{"evapotranspiration":3.8,"rainfall":69.233,"year":8,"week":2},{"evapotranspiration":4.8,"rainfall":41.733,"year":9,"week":2},{"evapotranspiration":4.8,"rainfall":99.367,"year":10,"week":2},{"evapotranspiration":6.1,"rainfall":9.1,"year":11,"week":2},{"evapotranspiration":4.4,"rainfall":32.8,"year":12,"week":2},{"evapotranspiration":5.8,"rainfall":4.567,"year":13,"week":2},{"evapotranspiration":5.0,"rainfall":98.8,"year":14,"week":2},{"evapotranspiration":6.0,"rainfall":50.8,"year":15,"week":2},{"evapotranspiration":6.0,"rainfall":67.633,"year":16,"week":2},{"evapotranspiration":6.2,"rainfall":9.367,"year":17,"week":2},{"evapotranspiration":4.6,"rainfall":35.033,"year":18,"week":2},{"evapotranspiration":5.1,"rainfall":85.7,"year":19,"week":2},{"evapotranspiration":4.1,"rainfall":6.067,"year":20,"week":2}],[{"evapotranspiration":4.9,"rainfall":38.267,"year":1,"week":3},{"evapotranspiration":6.7,"rainfall":117.5,"year":2,"week":3},{"evapotranspiration":4.9,"rainfall":59.567,"year":3,"week":3},{"evapotranspiration":7.0,"rainfall":50.233,"year":4,"week":3},{"evapotranspiration":6.2,"rainfall":7.5,"year":5,"week":3},{"evapotranspiration":5.6,"rainfall":14.667,"year":6,"week":3},{"evapotranspiration":5.8,"rainfall":32.933,"year":7,"week":3},{"evapotranspiration":5.1,"rainfall":49.067,"year":8,"week":3},{"evapotranspiration":9.3,"rainfall":0.3,"year":9,"week":3},{"evapotranspiration":7.5,"rainfall":7.167,"year":10,"week":3},{"evapotranspiration":5.4,"rainfall":58.7,"year":11,"week":3},{"evapotranspiration":5.3,"rainfall":90.667,"year":12,"week":3},{"evapotranspiration":4.1,"rainfall":86.333,"year":13,"week":3},{"evapotranspiration":6.6,"rainfall":53.467,"year":14,"week":3},{"evapotranspiration":6.9,"rainfall":7.267,"year":15,"week":3},{"evapotranspiration":7.4,"rainfall":71.733,"year":16,"week":3},{"evapotranspiration":7.0,"rainfall":57.133,"year":17,"week":3},{"evapotranspiration":6.5,"rainfall":41.267,"year":18,"week":3},{"evapotranspiration":5.4,"rainfall":50.867,"year":19,"week":3},{"evapotranspiration":8.5,"rainfall":0.0,"year":20,"week":3}],[{"evapotranspiration":5.5,"rainfall":25.4,"year":1,"week":4},{"evapotranspiration":6.1,"rainfall":21.367,"year":2,"week":4},{"evapotranspiration":9.9,"rainfall":4.9,"year":3,"week":4},{"evapotranspiration":6.9,"rainfall":67.0,"year":4,"week":4},{"evapotranspiration":6.2,"rainfall":34.067,"year":5,"week":4},{"evapotranspiration":7.6,"rainfall":18.3,"year":6,"week":4},{"evapotranspiration":6.6,"rainfall":29.9,"year":7,"week":4},{"evapotranspiration":5.6,"rainfall":18.233,"year":8,"week":4},{"evapotranspiration":7.8,"rainfall":65.167,"year":9,"week":4},{"evapotranspiration":7.7,"rainfall":30.467,"year":10,"week":4},{"evapotranspiration":8.4,"rainfall":0.233,"year":11,"week":4},{"evapotranspiration":6.2,"rainfall":83.133,"year":12,"week":4},{"evapotranspiration":6.5,"rainfall":30.6,"year":13,"week":4},{"evapotranspiration":9.7,"rainfall":67.533,"year":14,"week":4},{"evapotranspiration":9.7,"rainfall":0.0,"year":15,"week":4},{"evapotranspiration":9.0,"rainfall":24.067,"year":16,"week":4},{"evapotranspiration":8.0,"rainfall":84.633,"year":17,"week":4},{"evapotranspiration":7.3,"rainfall":82.667,"year":18,"week":4},{"evapotranspiration":7.0,"rainfall":28.6,"year":19,"week":4},{"evapotranspiration":6.6,"rainfall":82.333,"year":20,"week":4}],[{"evapotranspiration":9.8,"rainfall":27.367,"year":1,"week":5},{"evapotranspiration":7.9,"rainfall":45.867,"year":2,"week":5},{"evapotranspiration":11.2,"rainfall":2.333,"year":3,"week":5},{"evapotranspiration":9.9,"rainfall":54.3,"year":4,"week":5},{"evapotranspiration":6.9,"rainfall":47.3,"year":5,"week":5},{"evapotranspiration":10.2,"rainfall":1.733,"year":6,"week":5},{"evapotranspiration":8.4,"rainfall":40.233,"year":7,"week":5},{"evapotranspiration":7.6,"rainfall":4.733,"year":8,"week":5},{"evapotranspiration":11.9,"rainfall":0.0,"year":9,"week":5},{"evapotranspiration":10.3,"rainfall":0.0,"year":10,"week":5},{"evapotranspiration":9.1,"rainfall":46.333,"year":11,"week":5},{"evapotranspiration":9.0,"rainfall":14.933,"year":12,"week":5},{"evapotranspiration":8.9,"rainfall":62.433,"year":13,"week":5},{"evapotranspiration":9.8,"rainfall":22.3,"year":14,"week":5},{"evapotranspiration":10.5,"rainfall":20.333,"year":15,"week":5},{"evapotranspiration":10.8,"rainfall":3.2,"year":16,"week":5},{"evapotranspiration":9.5,"rainfall":20.7,"year":17,"week":5},{"evapotranspiration":8.6,"rainfall":5.267,"year":18,"week":5},{"evapotranspiration":8.9,"rainfall":8.867,"year":19,"week":5},{"evapotranspiration":9.8,"rainfall":5.567,"year":20,"week":5}],[{"evapotranspiration":8.5,"rainfall":16.2,"year":1,"week":6},{"evapotranspiration":9.7,"rainfall":1.933,"year":2,"week":6},{"evapotranspiration":11.4,"rainfall":23.067,"year":3,"week":6},{"evapotranspiration":9.9,"rainfall":63.533,"year":4,"week":6},{"evapotranspiration":10.2,"rainfall":66.833,"year":5,"week":6},{"evapotranspiration":10.2,"rainfall":5.4,"year":6,"week":6},{"evapotranspiration":9.4,"rainfall":54.6,"year":7,"week":6},{"evapotranspiration":7.8,"rainfall":16.467,"year":8,"week":6},{"evapotranspiration":9.1,"rainfall":14.1,"year":9,"week":6},{"evapotranspiration":8.9,"rainfall":47.467,"year":10,"week":6},{"evapotranspiration":9.5,"rainfall":24.367,"year":11,"week":6},{"evapotranspiration":12.1,"rainfall":17.267,"year":12,"week":6},{"evapotranspiration":10.3,"rainfall":32.2,"year":13,"week":6},{"evapotranspiration":7.0,"rainfall":117.4,"year":14,"week":6},{"evapotranspiration":14.5,"rainfall":1.0,"year":15,"week":6},{"evapotranspiration":10.7,"rainfall":57.067,"year":16,"week":6},{"evapotranspiration":11.5,"rainfall":13.4,"year":17,"week":6},{"evapotranspiration":9.0,"rainfall":27.6,"year":18,"week":6},{"evapotranspiration":7.9,"rainfall":212.233,"year":19,"week":6},{"evapotranspiration":10.5,"rainfall":13.6,"year":20,"week":6}],[{"evapotranspiration":8.8,"rainfall":94.567,"year":1,"week":7},{"evapotranspiration":10.9,"rainfall":15.067,"year":2,"week":7},{"evapotranspiration":13.2,"rainfall":98.2,"year":3,"week":7},{"evapotranspiration":14.2,"rainfall":6.5,"year":4,"week":7},{"evapotranspiration":12.4,"rainfall":25.433,"year":5,"week":7},{"evapotranspiration":12.4,"rainfall":13.4,"year":6,"week":7},{"evapotranspiration":10.6,"rainfall":34.733,"year":7,"week":7},{"evapotranspiration":12.5,"rainfall":5.667,"year":8,"week":7},{"evapotranspiration":11.8,"rainfall":108.7,"year":9,"week":7},{"evapotranspiration":11.2,"rainfall":3.667,"year":10,"week":7},{"evapotranspiration":12.6,"rainfall":30.833,"year":11,"week":7},{"evapotranspiration":11.1,"rainfall":83.9,"year":12,"week":7},{"evapotranspiration":11.2,"rainfall":15.133,"year":13,"week":7},{"evapotranspiration":12.3,"rainfall":58.967,"year":14,"week":7},{"evapotranspiration":12.2,"rainfall":50.533,"year":15,"week":7},{"evapotranspiration":13.9,"rainfall":52.433,"year":16,"week":7},{"evapotranspiration":10.6,"rainfall":32.8,"year":17,"week":7},{"evapotranspiration":11.0,"rainfall":97.85,"year":18,"week":7},{"evapotranspiration":10.9,"rainfall":24.4,"year":19,"week":7},{"evapotranspiration":9.9,"rainfall":29.567,"year":20,"week":7}],[{"evapotranspiration":14.3,"rainfall":7.9,"year":1,"week":8},{"evapotranspiration":12.5,"rainfall":48.3,"year":2,"week":8},{"evapotranspiration":15.8,"rainfall":14.967,"year":3,"week":8},{"evapotranspiration":14.5,"rainfall":2.067,"year":4,"week":8},{"evapotranspiration":15.7,"rainfall":3.833,"year":5,"week":8},{"evapotranspiration":11.8,"rainfall":48.4,"year":6,"week":8},{"evapotranspiration":13.1,"rainfall":37.967,"year":7,"week":8},{"evapotranspiration":11.0,"rainfall":46.3,"year":8,"week":8},{"evapotranspiration":13.1,"rainfall":23.3,"year":9,"week":8},{"evapotranspiration":15.6,"rainfall":1.667,"year":10,"week":8},{"evapotranspiration":12.5,"rainfall":33.167,"year":11,"week":8},{"evapotranspiration":15.6,"rainfall":13.667,"year":12,"week":8},{"evapotranspiration":15.5,"rainfall":7.4,"year":13,"week":8},{"evapotranspiration":15.5,"rainfall":31.267,"year":14,"week":8},{"evapotranspiration":15.4,"rainfall":4.233,"year":15,"week":8},{"evapotranspiration":13.6,"rainfall":19.2,"year":16,"week":8},{"evapotranspiration":11.8,"rainfall":28.6,"year":17,"week":8},{"evapotranspiration":9.2,"rainfall":45.483,"year":18,"week":8},{"evapotranspiration":14.6,"rainfall":21.533,"year":19,"week":8},{"evapotranspiration":9.4,"rainfall":110.7,"year":20,"week":8}],[{"evapotranspiration":9.3,"rainfall":123.267,"year":1,"week":9},{"evapotranspiration":15.4,"rainfall":12.0,"year":2,"week":9},{"evapotranspiration":19.8,"rainfall":6.233,"year":3,"week":9},{"evapotranspiration":12.6,"rainfall":31.9,"year":4,"week":9},{"evapotranspiration":18.9,"rainfall":0.0,"year":5,"week":9},{"evapotranspiration":17.0,"rainfall":5.133,"year":6,"week":9},{"evapotranspiration":15.8,"rainfall":10.467,"year":7,"week":9},{"evapotranspiration":11.8,"rainfall":58.767,"year":8,"week":9},{"evapotranspiration":12.8,"rainfall":13.933,"year":9,"week":9},{"evapotranspiration":21.8,"rainfall":0.0,"year":10,"week":9},{"evapotranspiration":14.9,"rainfall":22.333,"year":11,"week":9},{"evapotranspiration":16.4,"rainfall":1.167,"year":12,"week":9},{"evapotranspiration":12.2,"rainfall":74.4,"year":13,"week":9},{"evapotranspiration":18.0,"rainfall":15.333,"year":14,"week":9},{"evapotranspiration":16.0,"rainfall":13.067,"year":15,"week":9},{"evapotranspiration":12.6,"rainfall":15.667,"year":16,"week":9},{"evapotranspiration":16.9,"rainfall":43.4,"year":17,"week":9},{"evapotranspiration":18.0,"rainfall":35.867,"year":18,"week":9},{"evapotranspiration":14.8,"rainfall":52.833,"year":19,"week":9},{"evapotranspiration":11.7,"rainfall":134.3,"year":20,"week":9}],[{"evapotranspiration":15.3,"rainfall":62.3,"year":1,"week":10},{"evapotranspiration":16.7,"rainfall":20.8,"year":2,"week":10},{"evapotranspiration":18.3,"rainfall":56.967,"year":3,"week":10},{"evapotranspiration":15.1,"rainfall":31.833,"year":4,"week":10},{"evapotranspiration":19.7,"rainfall":51.633,"year":5,"week":10},{"evapotranspiration":15.8,"rainfall":10.667,"year":6,"week":10},{"evapotranspiration":12.7,"rainfall":94.6,"year":7,"week":10},{"evapotranspiration":14.7,"rainfall":11.433,"year":8,"week":10},{"evapotranspiration":16.7,"rainfall":116.233,"year":9,"week":10},{"evapotranspiration":16.9,"rainfall":55.667,"year":10,"week":10},{"evapotranspiration":16.0,"rainfall":61.3,"year":11,"week":10},{"evapotranspiration":19.0,"rainfall":8.7,"year":12,"week":10},{"evapotranspiration":15.6,"rainfall":45.0,"year":13,"week":10},{"evapotranspiration":20.8,"rainfall":6.367,"year":14,"week":10},{"evapotranspiration":19.6,"rainfall":53.467,"year":15,"week":10},{"evapotranspiration":19.4,"rainfall":19.767,"year":16,"week":10},{"evapotranspiration":21.1,"rainfall":10.467,"year":17,"week":10},{"evapotranspiration":17.3,"rainfall":26.4,"year":18,"week":10},{"evapotranspiration":18.9,"rainfall":19.733,"year":19,"week":10},{"evapotranspiration":16.7,"rainfall":48.533,"year":20,"week":10}],[{"evapotranspiration":17.2,"rainfall":15.633,"year":1,"week":11},{"evapotranspiration":15.8,"rainfall":12.05,"year":2,"week":11},{"evapotranspiration":21.7,"rainfall":8.933,"year":3,"week":11},{"evapotranspiration":17.1,"rainfall":38.6,"year":4,"week":11},{"evapotranspiration":17.0,"rainfall":35.867,"year":5,"week":11},{"evapotranspiration":20.9,"rainfall":7.067,"year":6,"week":11},{"evapotranspiration":16.3,"rainfall":47.933,"year":7,"week":11},{"evapotranspiration":16.0,"rainfall":89.467,"year":8,"week":11},{"evapotranspiration":15.6,"rainfall":66.9,"year":9,"week":11},{"evapotranspiration":22.2,"rainfall":7.767,"year":10,"week":11},{"evapotranspiration":18.1,"rainfall":63.667,"year":11,"week":11},{"evapotranspiration":12.9,"rainfall":48.467,"year":12,"week":11},{"evapotranspiration":11.0,"rainfall":85.033,"year":13,"week":11},{"evapotranspiration":18.7,"rainfall":22.667,"year":14,"week":11},{"evapotranspiration":13.7,"rainfall":126.633,"year":15,"week":11},{"evapotranspiration":17.3,"rainfall":23.433,"year":16,"week":11},{"evapotranspiration":17.7,"rainfall":33.367,"year":17,"week":11},{"evapotranspiration":16.9,"rainfall":8.2,"year":18,"week":11},{"evapotranspiration":22.6,"rainfall":2.133,"year":19,"week":11},{"evapotranspiration":15.8,"rainfall":18.433,"year":20,"week":11}],[{"evapotranspiration":19.1,"rainfall":38.8,"year":1,"week":12},{"evapotranspiration":17.7,"rainfall":64.7,"year":2,"week":12},{"evapotranspiration":21.0,"rainfall":17.667,"year":3,"week":12},{"evapotranspiration":24.6,"rainfall":2.067,"year":4,"week":12},{"evapotranspiration":21.5,"rainfall":33.567,"year":5,"week":12},{"evapotranspiration":19.9,"rainfall":27.267,"year":6,"week":12},{"evapotranspiration":20.6,"rainfall":44.2,"year":7,"week":12},{"evapotranspiration":18.0,"rainfall":9.367,"year":8,"week":12},{"evapotranspiration":19.1,"rainfall":76.333,"year":9,"week":12},{"evapotranspiration":17.3,"rainfall":9.033,"year":10,"week":12},{"evapotranspiration":18.3,"rainfall":41.0,"year":11,"week":12},{"evapotranspiration":20.1,"rainfall":29.333,"year":12,"week":12},{"evapotranspiration":17.2,"rainfall":47.2,"year":13,"week":12},{"evapotranspiration":24.9,"rainfall":11.833,"year":14,"week":12},{"evapotranspiration":20.4,"rainfall":29.933,"year":15,"week":12},{"evapotranspiration":23.7,"rainfall":38.167,"year":16,"week":12},{"evapotranspiration":22.1,"rainfall":13.967,"year":17,"week":12},{"evapotranspiration":23.1,"rainfall":34.133,"year":18,"week":12},{"evapotranspiration":20.9,"rainfall":9.933,"year":19,"week":12},{"evapotranspiration":24.4,"rainfall":5.067,"year":20,"week":12}],[{"evapotranspiration":19.8,"rainfall":34.4,"year":1,"week":13},{"evapotranspiration":20.5,"rainfall":17.7,"year":2,"week":13},{"evapotranspiration":19.0,"rainfall":15.533,"year":3,"week":13},{"evapotranspiration":24.1,"rainfall":20.967,"year":4,"week":13},{"evapotranspiration":19.4,"rainfall":5.4,"year":5,"week":13},{"evapotranspiration":19.7,"rainfall":20.867,"year":6,"week":13},{"evapotranspiration":25.2,"rainfall":12.967,"year":7,"week":13},{"evapotranspiration":22.8,"rainfall":17.733,"year":8,"week":13},{"evapotranspiration":29.8,"rainfall":0.0,"year":9,"week":13},{"evapotranspiration":17.7,"rainfall":19.933,"year":10,"week":13},{"evapotranspiration":27.0,"rainfall":4.4,"year":11,"week":13},{"evapotranspiration":19.9,"rainfall":48.1,"year":12,"week":13},{"evapotranspiration":18.6,"rainfall":16.0,"year":13,"week":13},{"evapotranspiration":31.8,"rainfall":0.0,"year":14,"week":13},{"evapotranspiration":22.1,"rainfall":16.8,"year":15,"week":13},{"evapotranspiration":21.0,"rainfall":19.333,"year":16,"week":13},{"evapotranspiration":22.6,"rainfall":2.333,"year":17,"week":13},{"evapotranspiration":23.5,"rainfall":1.2,"year":18,"week":13},{"evapotranspiration":19.7,"rainfall":17.867,"year":19,"week":13},{"evapotranspiration":25.5,"rainfall":21.633,"year":20,"week":13}],[{"evapotranspiration":30.0,"rainfall":5.0,"year":1,"week":14},{"evapotranspiration":23.5,"rainfall":26.55,"year":2,"week":14},{"evapotranspiration":20.0,"rainfall":192.867,"year":3,"week":14},{"evapotranspiration":24.7,"rainfall":58.433,"year":4,"week":14},{"evapotranspiration":23.1,"rainfall":66.9,"year":5,"week":14},{"evapotranspiration":22.4,"rainfall":26.467,"year":6,"week":14},{"evapotranspiration":21.2,"rainfall":34.6,"year":7,"week":14},{"evapotranspiration":20.7,"rainfall":60.833,"year":8,"week":14},{"evapotranspiration":25.8,"rainfall":3.0,"year":9,"week":14},{"evapotranspiration":22.6,"rainfall":12.133,"year":10,"week":14},{"evapotranspiration":25.2,"rainfall":5.067,"year":11,"week":14},{"evapotranspiration":20.6,"rainfall":12.367,"year":12,"week":14},{"evapotranspiration":22.5,"rainfall":15.767,"year":13,"week":14},{"evapotranspiration":28.5,"rainfall":9.0,"year":14,"week":14},{"evapotranspiration":29.8,"rainfall":26.533,"year":15,"week":14},{"evapotranspiration":28.6,"rainfall":8.4,"year":16,"week":14},{"evapotranspiration":26.6,"rainfall":4.267,"year":17,"week":14},{"evapotranspiration":22.1,"rainfall":22.533,"year":18,"week":14},{"evapotranspiration":24.4,"rainfall":10.0,"year":19,"week":14},{"evapotranspiration":27.9,"rainfall":3.2,"year":20,"week":14}],[{"evapotranspiration":22.5,"rainfall":23.5,"year":1,"week":15},{"evapotranspiration":27.5,"rainfall":40.833,"year":2,"week":15},{"evapotranspiration":21.3,"rainfall":65.633,"year":3,"week":15},{"evapotranspiration":18.6,"rainfall":39.6,"year":4,"week":15},{"evapotranspiration":27.3,"rainfall":27.467,"year":5,"week":15},{"evapotranspiration":22.6,"rainfall":25.667,"year":6,"week":15},{"evapotranspiration":22.5,"rainfall":21.733,"year":7,"week":15},{"evapotranspiration":23.6,"rainfall":15.2,"year":8,"week":15},{"evapotranspiration":28.0,"rainfall":23.833,"year":9,"week":15},{"evapotranspiration":23.8,"rainfall":52.433,"year":10,"week":15},{"evapotranspiration":20.7,"rainfall":14.7,"year":11,"week":15},{"evapotranspiration":22.5,"rainfall":18.867,"year":12,"week":15},{"evapotranspiration":24.4,"rainfall":8.133,"year":13,"week":15},{"evapotranspiration":32.8,"rainfall":3.0,"year":14,"week":15},{"evapotranspiration":28.7,"rainfall":14.367,"year":15,"week":15},{"evapotranspiration":29.6,"rainfall":0.0,"year":16,"week":15},{"evapotranspiration":30.0,"rainfall":77.267,"year":17,"week":15},{"evapotranspiration":24.4,"rainfall":17.333,"year":18,"week":15},{"evapotranspiration":27.8,"rainfall":20.933,"year":19,"week":15},{"evapotranspiration":28.7,"rainfall":52.933,"year":20,"week":15}],[{"evapotranspiration":21.9,"rainfall":26.133,"year":1,"week":16},{"evapotranspiration":32.2,"rainfall":0.0,"year":2,"week":16},{"evapotranspiration":32.0,"rainfall":31.0,"year":3,"week":16},{"evapotranspiration":29.3,"rainfall":0.567,"year":4,"week":16},{"evapotranspiration":24.5,"rainfall":16.467,"year":5,"week":16},{"evapotranspiration":25.6,"rainfall":7.2,"year":6,"week":16},{"evapotranspiration":22.4,"rainfall":10.133,"year":7,"week":16},{"evapotranspiration":26.5,"rainfall":29.633,"year":8,"week":16},{"evapotranspiration":28.7,"rainfall":2.867,"year":9,"week":16},{"evapotranspiration":26.8,"rainfall":28.9,"year":10,"week":16},{"evapotranspiration":26.8,"rainfall":20.533,"year":11,"week":16},{"evapotranspiration":28.4,"rainfall":0.0,"year":12,"week":16},{"evapotranspiration":21.8,"rainfall":2.933,"year":13,"week":16},{"evapotranspiration":31.6,"rainfall":17.1,"year":14,"week":16},{"evapotranspiration":34.7,"rainfall":0.833,"year":15,"week":16},{"evapotranspiration":19.7,"rainfall":44.4,"year":16,"week":16},{"evapotranspiration":34.4,"rainfall":0.0,"year":17,"week":16},{"evapotranspiration":26.0,"rainfall":36.167,"year":18,"week":16},{"evapotranspiration":31.8,"rainfall":12.467,"year":19,"week":16},{"evapotranspiration":21.4,"rainfall":35.667,"year":20,"week":16}],[{"evapotranspiration":22.2,"rainfall":23.933,"year":1,"week":17},{"evapotranspiration":29.6,"rainfall":16.967,"year":2,"week":17},{"evapotranspiration":28.5,"rainfall":29.0,"year":3,"week":17},{"evapotranspiration":23.2,"rainfall":14.833,"year":4,"week":17},{"evapotranspiration":22.9,"rainfall":47.633,"year":5,"week":17},{"evapotranspiration":26.5,"rainfall":20.7,"year":6,"week":17},{"evapotranspiration":30.0,"rainfall":5.0,"year":7,"week":17},{"evapotranspiration":21.5,"rainfall":45.133,"year":8,"week":17},{"evapotranspiration":23.3,"rainfall":62.517,"year":9,"week":17},{"evapotranspiration":27.6,"rainfall":7.233,"year":10,"week":17},{"evapotranspiration":30.5,"rainfall":4.333,"year":11,"week":17},{"evapotranspiration":27.9,"rainfall":7.767,"year":12,"week":17},{"evapotranspiration":26.0,"rainfall":12.0,"year":13,"week":17},{"evapotranspiration":34.9,"rainfall":26.9,"year":14,"week":17},{"evapotranspiration":33.4,"rainfall":11.0,"year":15,"week":17},{"evapotranspiration":35.4,"rainfall":1.967,"year":16,"week":17},{"evapotranspiration":38.8,"rainfall":8.067,"year":17,"week":17},{"evapotranspiration":20.9,"rainfall":21.767,"year":18,"week":17},{"evapotranspiration":20.8,"rainfall":68.267,"year":19,"week":17},{"evapotranspiration":36.1,"rainfall":11.733,"year":20,"week":17}],[{"evapotranspiration":32.2,"rainfall":6.267,"year":1,"week":18},{"evapotranspiration":20.6,"rainfall":29.7,"year":2,"week":18},{"evapotranspiration":29.8,"rainfall":22.5,"year":3,"week":18},{"evapotranspiration":28.3,"rainfall":27.867,"year":4,"week":18},{"evapotranspiration":20.7,"rainfall":109.867,"year":5,"week":18},{"evapotranspiration":29.6,"rainfall":14.467,"year":6,"week":18},{"evapotranspiration":21.0,"rainfall":57.733,"year":7,"week":18},{"evapotranspiration":25.4,"rainfall":31.633,"year":8,"week":18},{"evapotranspiration":30.9,"rainfall":2.9,"year":9,"week":18},{"evapotranspiration":26.4,"rainfall":14.967,"year":10,"week":18},{"evapotranspiration":35.3,"rainfall":14.333,"year":11,"week":18},{"evapotranspiration":32.3,"rainfall":40.333,"year":12,"week":18},{"evapotranspiration":36.0,"rainfall":2.567,"year":13,"week":18},{"evapotranspiration":32.9,"rainfall":4.933,"year":14,"week":18},{"evapotranspiration":34.3,"rainfall":26.6,"year":15,"week":18},{"evapotranspiration":33.8,"rainfall":0.0,"year":16,"week":18},{"evapotranspiration":32.6,"rainfall":79.2,"year":17,"week":18},{"evapotranspiration":32.6,"rainfall":5.933,"year":18,"week":18},{"evapotranspiration":33.6,"rainfall":25.8,"year":19,"week":18},{"evapotranspiration":30.7,"rainfall":5.967,"year":20,"week":18}],[{"evapotranspiration":22.3,"rainfall":26.233,"year":1,"week":19},{"evapotranspiration":21.8,"rainfall":201.633,"year":2,"week":19},{"evapotranspiration":33.1,"rainfall":22.333,"year":3,"week":19},{"evapotranspiration":33.8,"rainfall":37.1,"year":4,"week":19},{"evapotranspiration":24.9,"rainfall":88.833,"year":5,"week":19},{"evapotranspiration":31.2,"rainfall":29.467,"year":6,"week":19},{"evapotranspiration":33.7,"rainfall":7.733,"year":7,"week":19},{"evapotranspiration":22.3,"rainfall":52.367,"year":8,"week":19},{"evapotranspiration":27.1,"rainfall":55.033,"year":9,"week":19},{"evapotranspiration":28.5,"rainfall":30.267,"year":10,"week":19},{"evapotranspiration":26.7,"rainfall":50.367,"year":11,"week":19},{"evapotranspiration":33.1,"rainfall":4.6,"year":12,"week":19},{"evapotranspiration":18.6,"rainfall":89.167,"year":13,"week":19},{"evapotranspiration":32.9,"rainfall":15.867,"year":14,"week":19},{"evapotranspiration":35.4,"rainfall":62.1,"year":15,"week":19},{"evapotranspiration":26.2,"rainfall":46.967,"year":16,"week":19},{"evapotranspiration":23.0,"rainfall":142.467,"year":17,"week":19},{"evapotranspiration":32.9,"rainfall":2.267,"year":18,"week":19},{"evapotranspiration":28.9,"rainfall":15.2,"year":19,"week":19},{"evapotranspiration":25.8,"rainfall":26.4,"year":20,"week":19}],[{"evapotranspiration":27.8,"rainfall":5.367,"year":1,"week":20},{"evapotranspiration":31.8,"rainfall":4.467,"year":2,"week":20},{"evapotranspiration":31.5,"rainfall":22.533,"year":3,"week":20},{"evapotranspiration":27.4,"rainfall":16.133,"year":4,"week":20},{"evapotranspiration":29.4,"rainfall":42.2,"year":5,"week":20},{"evapotranspiration":27.9,"rainfall":19.8,"year":6,"week":20},{"evapotranspiration":30.7,"rainfall":56.4,"year":7,"week":20},{"evapotranspiration":29.9,"rainfall":8.0,"year":8,"week":20},{"evapotranspiration":27.4,"rainfall":119.9,"year":9,"week":20},{"evapotranspiration":36.4,"rainfall":0.0,"year":10,"week":20},{"evapotranspiration":27.5,"rainfall":31.033,"year":11,"week":20},{"evapotranspiration":30.8,"rainfall":34.2,"year":12,"week":20},{"evapotranspiration":39.8,"rainfall":3.5,"year":13,"week":20},{"evapotranspiration":22.3,"rainfall":87.767,"year":14,"week":20},{"evapotranspiration":23.1,"rainfall":165.333,"year":15,"week":20},{"evapotranspiration":36.8,"rainfall":5.0,"year":16,"week":20},{"evapotranspiration":35.0,"rainfall":0.067,"year":17,"week":20},{"evapotranspiration":25.9,"rainfall":28.2,"year":18,"week":20},{"evapotranspiration":31.6,"rainfall":15.533,"year":19,"week":20},{"evapotranspiration":34.0,"rainfall":0.667,"year":20,"week":20}],[{"evapotranspiration":34.9,"rainfall":22.233,"year":1,"week":21},{"evapotranspiration":30.8,"rainfall":46.133,"year":2,"week":21},{"evapotranspiration":29.1,"rainfall":31.867,"year":3,"week":21},{"evapotranspiration":37.7,"rainfall":1.0,"year":4,"week":21},{"evapotranspiration":24.9,"rainfall":111.967,"year":5,"week":21},{"evapotranspiration":29.0,"rainfall":46.033,"year":6,"week":21},{"evapotranspiration":36.4,"rainfall":9.9,"year":7,"week":21},{"evapotranspiration":26.2,"rainfall":31.3,"year":8,"week":21},{"evapotranspiration":30.7,"rainfall":71.167,"year":9,"week":21},{"evapotranspiration":24.6,"rainfall":51.667,"year":10,"week":21},{"evapotranspiration":29.2,"rainfall":40.4,"year":11,"week":21},{"evapotranspiration":27.6,"rainfall":25.8,"year":12,"week":21},{"evapotranspiration":42.2,"rainfall":3.467,"year":13,"week":21},{"evapotranspiration":30.8,"rainfall":72.0,"year":14,"week":21},{"evapotranspiration":30.7,"rainfall":53.2,"year":15,"week":21},{"evapotranspiration":33.0,"rainfall":19.667,"year":16,"week":21},{"evapotranspiration":42.8,"rainfall":0.0,"year":17,"week":21},{"evapotranspiration":24.7,"rainfall":155.0,"year":18,"week":21},{"evapotranspiration":29.0,"rainfall":8.633,"year":19,"week":21},{"evapotranspiration":35.7,"rainfall":25.667,"year":20,"week":21}],[{"evapotranspiration":35.2,"rainfall":18.533,"year":1,"week":22},{"evapotranspiration":38.2,"rainfall":0.267,"year":2,"week":22},{"evapotranspiration":21.2,"rainfall":2.067,"year":3,"week":22},{"evapotranspiration":27.0,"rainfall":68.5,"year":4,"week":22},{"evapotranspiration":28.1,"rainfall":41.4,"year":5,"week":22},{"evapotranspiration":34.7,"rainfall":8.667,"year":6,"week":22},{"evapotranspiration":25.8,"rainfall":29.2,"year":7,"week":22},{"evapotranspiration":23.9,"rainfall":43.967,"year":8,"week":22},{"evapotranspiration":29.2,"rainfall":3.3,"year":9,"week":22},{"evapotranspiration":34.3,"rainfall":1.933,"year":10,"week":22},{"evapotranspiration":18.7,"rainfall":5.167,"year":11,"week":22},{"evapotranspiration":30.4,"rainfall":37.967,"year":12,"week":22},{"evapotranspiration":40.9,"rainfall":6.7,"year":13,"week":22},{"evapotranspiration":22.7,"rainfall":13.067,"year":14,"week":22},{"evapotranspiration":34.8,"rainfall":122.0,"year":15,"week":22},{"evapotranspiration":28.6,"rainfall":218.0,"year":16,"week":22},{"evapotranspiration":28.4,"rainfall":69.433,"year":17,"week":22},{"evapotranspiration":34.8,"rainfall":0.067,"year":18,"week":22},{"evapotranspiration":35.6,"rainfall":38.067,"year":19,"week":22},{"evapotranspiration":30.3,"rainfall":0.0,"year":20,"week":22}],[{"evapotranspiration":40.1,"rainfall":26.467,"year":1,"week":23},{"evapotranspiration":22.5,"rainfall":0.0,"year":2,"week":23},{"evapotranspiration":43.1,"rainfall":0.0,"year":3,"week":23},{"evapotranspiration":31.8,"rainfall":14.533,"year":4,"week":23},{"evapotranspiration":39.9,"rainfall":9.667,"year":5,"week":23},{"evapotranspiration":44.5,"rainfall":8.933,"year":6,"week":23},{"evapotranspiration":33.5,"rainfall":26.467,"year":7,"week":23},{"evapotranspiration":23.5,"rainfall":0.0,"year":8,"week":23},{"evapotranspiration":28.2,"rainfall":36.533,"year":9,"week":23},{"evapotranspiration":32.5,"rainfall":24.267,"year":10,"week":23},{"evapotranspiration":32.6,"rainfall":15.133,"year":11,"week":23},{"evapotranspiration":40.6,"rainfall":56.0,"year":12,"week":23},{"evapotranspiration":20.2,"rainfall":17.333,"year":13,"week":23},{"evapotranspiration":38.4,"rainfall":3.8,"year":14,"week":23},{"evapotranspiration":41.2,"rainfall":7.433,"year":15,"week":23},{"evapotranspiration":31.2,"rainfall":79.233,"year":16,"week":23},{"evapotranspiration":38.4,"rainfall":36.067,"year":17,"week":23},{"evapotranspiration":46.0,"rainfall":12.267,"year":18,"week":23},{"evapotranspiration":23.3,"rainfall":5.0,"year":19,"week":23},{"evapotranspiration":28.9,"rainfall":36.8,"year":20,"week":23}],[{"evapotranspiration":27.1,"rainfall":38.0,"year":1,"week":24},{"evapotranspiration":37.1,"rainfall":1.567,"year":2,"week":24},{"evapotranspiration":26.9,"rainfall":62.9,"year":3,"week":24},{"evapotranspiration":33.1,"rainfall":0.667,"year":4,"week":24},{"evapotranspiration":32.7,"rainfall":7.767,"year":5,"week":24},{"evapotranspiration":22.4,"rainfall":65.733,"year":6,"week":24},{"evapotranspiration":22.2,"rainfall":162.867,"year":7,"week":24},{"evapotranspiration":37.0,"rainfall":3.2,"year":8,"week":24},{"evapotranspiration":37.7,"rainfall":14.467,"year":9,"week":24},{"evapotranspiration":35.3,"rainfall":0.667,"year":10,"week":24},{"evapotranspiration":26.8,"rainfall":99.6,"year":11,"week":24},{"evapotranspiration":33.7,"rainfall":2.767,"year":12,"week":24},{"evapotranspiration":38.9,"rainfall":17.467,"year":13,"week":24},{"evapotranspiration":33.8,"rainfall":18.0,"year":14,"week":24},{"evapotranspiration":39.0,"rainfall":2.8,"year":15,"week":24},{"evapotranspiration":34.2,"rainfall":38.6,"year":16,"week":24},{"evapotranspiration":39.2,"rainfall":0.067,"year":17,"week":24},{"evapotranspiration":36.8,"rainfall":9.933,"year":18,"week":24},{"evapotranspiration":39.4,"rainfall":13.0,"year":19,"week":24},{"evapotranspiration":33.7,"rainfall":7.533,"year":20,"week":24}],[{"evapotranspiration":35.5,"rainfall":5.9,"year":1,"week":25},{"evapotranspiration":31.8,"rainfall":3.4,"year":2,"week":25},{"evapotranspiration":28.1,"rainfall":55.333,"year":3,"week":25},{"evapotranspiration":32.0,"rainfall":16.367,"year":4,"week":25},{"evapotranspiration":32.0,"rainfall":2.433,"year":5,"week":25},{"evapotranspiration":29.2,"rainfall":35.1,"year":6,"week":25},{"evapotranspiration":34.0,"rainfall":0.333,"year":7,"week":25},{"evapotranspiration":37.4,"rainfall":0.0,"year":8,"week":25},{"evapotranspiration":36.0,"rainfall":4.9,"year":9,"week":25},{"evapotranspiration":31.7,"rainfall":3.4,"year":10,"week":25},{"evapotranspiration":30.8,"rainfall":14.3,"year":11,"week":25},{"evapotranspiration":41.3,"rainfall":0.0,"year":12,"week":25},{"evapotranspiration":35.1,"rainfall":34.333,"year":13,"week":25},{"evapotranspiration":34.1,"rainfall":46.533,"year":14,"week":25},{"evapotranspiration":32.3,"rainfall":141.0,"year":15,"week":25},{"evapotranspiration":34.2,"rainfall":0.0,"year":16,"week":25},{"evapotranspiration":30.2,"rainfall":6.533,"year":17,"week":25},{"evapotranspiration":36.1,"rainfall":2.133,"year":18,"week":25},{"evapotranspiration":44.0,"rainfall":0.733,"year":19,"week":25},{"evapotranspiration":38.0,"rainfall":32.133,"year":20,"week":25}],[{"evapotranspiration":31.4,"rainfall":12.233,"year":1,"week":26},{"evapotranspiration":25.3,"rainfall":112.133,"year":2,"week":26},{"evapotranspiration":35.2,"rainfall":28.3,"year":3,"week":26},{"evapotranspiration":27.9,"rainfall":26.133,"year":4,"week":26},{"evapotranspiration":28.5,"rainfall":11.5,"year":5,"week":26},{"evapotranspiration":33.2,"rainfall":5.1,"year":6,"week":26},{"evapotranspiration":30.6,"rainfall":7.9,"year":7,"week":26},{"evapotranspiration":32.1,"rainfall":20.933,"year":8,"week":26},{"evapotranspiration":40.1,"rainfall":0.0,"year":9,"week":26},{"evapotranspiration":28.9,"rainfall":168.4,"year":10,"week":26},{"evapotranspiration":30.9,"rainfall":14.1,"year":11,"week":26},{"evapotranspiration":29.6,"rainfall":61.867,"year":12,"week":26},{"evapotranspiration":36.0,"rainfall":5.133,"year":13,"week":26},{"evapotranspiration":38.1,"rainfall":11.167,"year":14,"week":26},{"evapotranspiration":25.3,"rainfall":199.667,"year":15,"week":26},{"evapotranspiration":32.0,"rainfall":5.9,"year":16,"week":26},{"evapotranspiration":39.4,"rainfall":0.0,"year":17,"week":26},{"evapotranspiration":31.9,"rainfall":43.933,"year":18,"week":26},{"evapotranspiration":40.8,"rainfall":1.133,"year":19,"week":26},{"evapotranspiration":37.0,"rainfall":11.867,"year":20,"week":26}],[{"evapotranspiration":32.0,"rainfall":0.0,"year":1,"week":27},{"evapotranspiration":33.5,"rainfall":3.767,"year":2,"week":27},{"evapotranspiration":31.6,"rainfall":2.5,"year":3,"week":27},{"evapotranspiration":28.8,"rainfall":19.8,"year":4,"week":27},{"evapotranspiration":29.6,"rainfall":16.967,"year":5,"week":27},{"evapotranspiration":36.2,"rainfall":0.667,"year":6,"week":27},{"evapotranspiration":33.5,"rainfall":0.0,"year":7,"week":27},{"evapotranspiration":32.8,"rainfall":55.433,"year":8,"week":27},{"evapotranspiration":26.8,"rainfall":74.833,"year":9,"week":27},{"evapotranspiration":29.3,"rainfall":45.7,"year":10,"week":27},{"evapotranspiration":35.3,"rainfall":23.867,"year":11,"week":27},{"evapotranspiration":34.5,"rainfall":13.633,"year":12,"week":27},{"evapotranspiration":36.5,"rainfall":1.0,"year":13,"week":27},{"evapotranspiration":34.0,"rainfall":97.967,"year":14,"week":27},{"evapotranspiration":31.1,"rainfall":2.2,"year":15,"week":27},{"evapotranspiration":30.2,"rainfall":1.233,"year":16,"week":27},{"evapotranspiration":38.1,"rainfall":0.0,"year":17,"week":27},{"evapotranspiration":33.8,"rainfall":9.267,"year":18,"week":27},{"evapotranspiration":36.6,"rainfall":4.333,"year":19,"week":27},{"evapotranspiration":24.4,"rainfall":94.8,"year":20,"week":27}],[{"evapotranspiration":29.3,"rainfall":25.867,"year":1,"week":28},{"evapotranspiration":37.2,"rainfall":0.0,"year":2,"week":28},{"evapotranspiration":32.9,"rainfall":0.133,"year":3,"week":28},{"evapotranspiration":33.2,"rainfall":2.167,"year":4,"week":28},{"evapotranspiration":27.9,"rainfall":48.833,"year":5,"week":28},{"evapotranspiration":26.7,"rainfall":16.267,"year":6,"week":28},{"evapotranspiration":32.8,"rainfall":2.533,"year":7,"week":28},{"evapotranspiration":20.7,"rainfall":145.367,"year":8,"week":28},{"evapotranspiration":33.6,"rainfall":25.933,"year":9,"week":28},{"evapotranspiration":31.5,"rainfall":60.333,"year":10,"week":28},{"evapotranspiration":27.4,"rainfall":61.167,"year":11,"week":28},{"evapotranspiration":26.6,"rainfall":9.6,"year":12,"week":28},{"evapotranspiration":36.8,"rainfall":5.667,"year":13,"week":28},{"evapotranspiration":24.6,"rainfall":20.5,"year":14,"week":28},{"evapotranspiration":30.3,"rainfall":22.2,"year":15,"week":28},{"evapotranspiration":31.4,"rainfall":6.667,"year":16,"week":28},{"evapotranspiration":31.7,"rainfall":39.667,"year":17,"week":28},{"evapotranspiration":27.3,"rainfall":101.133,"year":18,"week":28},{"evapotranspiration":29.5,"rainfall":20.167,"year":19,"week":28},{"evapotranspiration":28.8,"rainfall":1.667,"year":20,"week":28}],[{"evapotranspiration":29.0,"rainfall":4.367,"year":1,"week":29},{"evapotranspiration":28.5,"rainfall":5.1,"year":2,"week":29},{"evapotranspiration":26.6,"rainfall":2.133,"year":3,"week":29},{"evapotranspiration":24.7,"rainfall":15.333,"year":4,"week":29},{"evapotranspiration":16.6,"rainfall":229.133,"year":5,"week":29},{"evapotranspiration":19.7,"rainfall":36.6,"year":6,"week":29},{"evapotranspiration":29.7,"rainfall":0.067,"year":7,"week":29},{"evapotranspiration":25.8,"rainfall":29.667,"year":8,"week":29},{"evapotranspiration":31.3,"rainfall":6.233,"year":9,"week":29},{"evapotranspiration":31.4,"rainfall":0.8,"year":10,"week":29},{"evapotranspiration":28.7,"rainfall":2.133,"year":11,"week":29},{"evapotranspiration":24.6,"rainfall":19.467,"year":12,"week":29},{"evapotranspiration":31.1,"rainfall":29.3,"year":13,"week":29},{"evapotranspiration":34.7,"rainfall":0.5,"year":14,"week":29},{"evapotranspiration":24.5,"rainfall":48.167,"year":15,"week":29},{"evapotranspiration":36.2,"rainfall":2.2,"year":16,"week":29},{"evapotranspiration":28.2,"rainfall":0.333,"year":17,"week":29},{"evapotranspiration":28.1,"rainfall":0.333,"year":18,"week":29},{"evapotranspiration":22.5,"rainfall":126.933,"year":19,"week":29},{"evapotranspiration":18.0,"rainfall":114.45,"year":20,"week":29}],[{"evapotranspiration":23.7,"rainfall":85.6,"year":1,"week":30},{"evapotranspiration":24.5,"rainfall":46.133,"year":2,"week":30},{"evapotranspiration":23.1,"rainfall":28.1,"year":3,"week":30},{"evapotranspiration":32.1,"rainfall":0.0,"year":4,"week":30},{"evapotranspiration":24.5,"rainfall":60.1,"year":5,"week":30},{"evapotranspiration":24.7,"rainfall":19.4,"year":6,"week":30},{"evapotranspiration":25.5,"rainfall":13.133,"year":7,"week":30},{"evapotranspiration":23.5,"rainfall":43.933,"year":8,"week":30},{"evapotranspiration":31.7,"rainfall":4.733,"year":9,"week":30},{"evapotranspiration":30.0,"rainfall":0.0,"year":10,"week":30},{"evapotranspiration":30.6,"rainfall":1.467,"year":11,"week":30},{"evapotranspiration":24.4,"rainfall":60.467,"year":12,"week":30},{"evapotranspiration":25.2,"rainfall":64.967,"year":13,"week":30},{"evapotranspiration":29.7,"rainfall":11.4,"year":14,"week":30},{"evapotranspiration":23.6,"rainfall":37.733,"year":15,"week":30},{"evapotranspiration":33.2,"rainfall":0.0,"year":16,"week":30},{"evapotranspiration":31.6,"rainfall":19.867,"year":17,"week":30},{"evapotranspiration":33.0,"rainfall":12.567,"year":18,"week":30},{"evapotranspiration":32.6,"rainfall":7.167,"year":19,"week":30},{"evapotranspiration":32.7,"rainfall":2.0,"year":20,"week":30}],[{"evapotranspiration":25.7,"rainfall":21.467,"year":1,"week":31},{"evapotranspiration":25.0,"rainfall":30.333,"year":2,"week":31},{"evapotranspiration":24.7,"rainfall":34.5,"year":3,"week":31},{"evapotranspiration":26.8,"rainfall":51.6,"year":4,"week":31},{"evapotranspiration":28.1,"rainfall":14.767,"year":5,"week":31},{"evapotranspiration":23.8,"rainfall":17.767,"year":6,"week":31},{"evapotranspiration":12.0,"rainfall":130.067,"year":7,"week":31},{"evapotranspiration":20.5,"rainfall":144.267,"year":8,"week":31},{"evapotranspiration":25.7,"rainfall":4.6,"year":9,"week":31},{"evapotranspiration":26.3,"rainfall":0.9,"year":10,"week":31},{"evapotranspiration":25.0,"rainfall":47.967,"year":11,"week":31},{"evapotranspiration":22.4,"rainfall":95.533,"year":12,"week":31},{"evapotranspiration":22.9,"rainfall":145.667,"year":13,"week":31},{"evapotranspiration":23.0,"rainfall":69.533,"year":14,"week":31},{"evapotranspiration":23.5,"rainfall":42.667,"year":15,"week":31},{"evapotranspiration":31.3,"rainfall":0.067,"year":16,"week":31},{"evapotranspiration":32.6,"rainfall":0.0,"year":17,"week":31},{"evapotranspiration":27.4,"rainfall":26.867,"year":18,"week":31},{"evapotranspiration":23.8,"rainfall":45.6,"year":19,"week":31},{"evapotranspiration":27.4,"rainfall":33.767,"year":20,"week":31}],[{"evapotranspiration":18.8,"rainfall":82.5,"year":1,"week":32},{"evapotranspiration":29.0,"rainfall":13.033,"year":2,"week":32},{"evapotranspiration":18.3,"rainfall":31.833,"year":3,"week":32},{"evapotranspiration":25.0,"rainfall":5.833,"year":4,"week":32},{"evapotranspiration":20.8,"rainfall":51.5,"year":5,"week":32},{"evapotranspiration":26.9,"rainfall":3.167,"year":6,"week":32},{"evapotranspiration":19.3,"rainfall":48.233,"year":7,"week":32},{"evapotranspiration":21.1,"rainfall":12.267,"year":8,"week":32},{"evapotranspiration":24.0,"rainfall":0.0,"year":9,"week":32},{"evapotranspiration":18.0,"rainfall":18.267,"year":10,"week":32},{"evapotranspiration":23.3,"rainfall":6.433,"year":11,"week":32},{"evapotranspiration":20.6,"rainfall":19.433,"year":12,"week":32},{"evapotranspiration":22.4,"rainfall":182.333,"year":13,"week":32},{"evapotranspiration":25.7,"rainfall":0.5,"year":14,"week":32},{"evapotranspiration":20.8,"rainfall":4.133,"year":15,"week":32},{"evapotranspiration":26.3,"rainfall":2.067,"year":16,"week":32},{"evapotranspiration":25.7,"rainfall":0.767,"year":17,"week":32},{"evapotranspiration":23.6,"rainfall":18.333,"year":18,"week":32},{"evapotranspiration":25.6,"rainfall":2.1,"year":19,"week":32},{"evapotranspiration":15.3,"rainfall":253.267,"year":20,"week":32}],[{"evapotranspiration":20.3,"rainfall":42.3,"year":1,"week":33},{"evapotranspiration":19.8,"rainfall":176.933,"year":2,"week":33},{"evapotranspiration":24.1,"rainfall":0.0,"year":3,"week":33},{"evapotranspiration":20.8,"rainfall":6.867,"year":4,"week":33},{"evapotranspiration":21.7,"rainfall":1.2,"year":5,"week":33},{"evapotranspiration":21.4,"rainfall":15.4,"year":6,"week":33},{"evapotranspiration":15.6,"rainfall":49.167,"year":7,"week":33},{"evapotranspiration":24.4,"rainfall":0.0,"year":8,"week":33},{"evapotranspiration":20.2,"rainfall":20.467,"year":9,"week":33},{"evapotranspiration":18.3,"rainfall":8.867,"year":10,"week":33},{"evapotranspiration":18.9,"rainfall":62.167,"year":11,"week":33},{"evapotranspiration":21.7,"rainfall":8.067,"year":12,"week":33},{"evapotranspiration":19.1,"rainfall":4.2,"year":13,"week":33},{"evapotranspiration":28.1,"rainfall":5.833,"year":14,"week":33},{"evapotranspiration":19.2,"rainfall":50.533,"year":15,"week":33},{"evapotranspiration":24.7,"rainfall":9.267,"year":16,"week":33},{"evapotranspiration":23.2,"rainfall":66.267,"year":17,"week":33},{"evapotranspiration":24.5,"rainfall":53.0,"year":18,"week":33},{"evapotranspiration":16.8,"rainfall":132.733,"year":19,"week":33},{"evapotranspiration":23.7,"rainfall":21.867,"year":20,"week":33}],[{"evapotranspiration":18.4,"rainfall":3.3,"year":1,"week":34},{"evapotranspiration":19.1,"rainfall":3.4,"year":2,"week":34},{"evapotranspiration":17.6,"rainfall":19.367,"year":3,"week":34},{"evapotranspiration":17.9,"rainfall":2.633,"year":4,"week":34},{"evapotranspiration":20.7,"rainfall":5.533,"year":5,"week":34},{"evapotranspiration":22.8,"rainfall":10.0,"year":6,"week":34},{"evapotranspiration":21.4,"rainfall":36.033,"year":7,"week":34},{"evapotranspiration":19.4,"rainfall":7.333,"year":8,"week":34},{"evapotranspiration":18.4,"rainfall":72.5,"year":9,"week":34},{"evapotranspiration":15.9,"rainfall":69.733,"year":10,"week":34},{"evapotranspiration":20.3,"rainfall":0.9,"year":11,"week":34},{"evapotranspiration":23.4,"rainfall":0.0,"year":12,"week":34},{"evapotranspiration":18.8,"rainfall":37.8,"year":13,"week":34},{"evapotranspiration":14.0,"rainfall":104.867,"year":14,"week":34},{"evapotranspiration":15.3,"rainfall":159.633,"year":15,"week":34},{"evapotranspiration":19.7,"rainfall":38.867,"year":16,"week":34},{"evapotranspiration":21.9,"rainfall":7.467,"year":17,"week":34},{"evapotranspiration":17.7,"rainfall":26.967,"year":18,"week":34},{"evapotranspiration":15.9,"rainfall":83.0,"year":19,"week":34},{"evapotranspiration":19.3,"rainfall":14.067,"year":20,"week":34}],[{"evapotranspiration":15.7,"rainfall":20.067,"year":1,"week":35},{"evapotranspiration":18.6,"rainfall":4.733,"year":2,"week":35},{"evapotranspiration":15.9,"rainfall":24.233,"year":3,"week":35},{"evapotranspiration":17.2,"rainfall":4.6,"year":4,"week":35},{"evapotranspiration":16.4,"rainfall":8.533,"year":5,"week":35},{"evapotranspiration":18.5,"rainfall":19.633,"year":6,"week":35},{"evapotranspiration":14.8,"rainfall":91.2,"year":7,"week":35},{"evapotranspiration":19.3,"rainfall":0.0,"year":8,"week":35},{"evapotranspiration":18.5,"rainfall":19.967,"year":9,"week":35},{"evapotranspiration":14.4,"rainfall":79.033,"year":10,"week":35},{"evapotranspiration":12.3,"rainfall":183.567,"year":11,"week":35},{"evapotranspiration":16.1,"rainfall":25.4,"year":12,"week":35},{"evapotranspiration":19.5,"rainfall":0.667,"year":13,"week":35},{"evapotranspiration":16.1,"rainfall":40.033,"year":14,"week":35},{"evapotranspiration":21.5,"rainfall":6.067,"year":15,"week":35},{"evapotranspiration":21.2,"rainfall":6.6,"year":16,"week":35},{"evapotranspiration":22.3,"rainfall":3.267,"year":17,"week":35},{"evapotranspiration":19.1,"rainfall":17.833,"year":18,"week":35},{"evapotranspiration":16.8,"rainfall":19.667,"year":19,"week":35},{"evapotranspiration":17.5,"rainfall":124.133,"year":20,"week":35}],[{"evapotranspiration":17.5,"rainfall":1.2,"year":1,"week":36},{"evapotranspiration":14.5,"rainfall":26.933,"year":2,"week":36},{"evapotranspiration":9.6,"rainfall":77.1,"year":3,"week":36},{"evapotranspiration":9.4,"rainfall":55.833,"year":4,"week":36},{"evapotranspiration":11.6,"rainfall":142.367,"year":5,"week":36},{"evapotranspiration":12.9,"rainfall":18.333,"year":6,"week":36},{"evapotranspiration":17.5,"rainfall":9.133,"year":7,"week":36},{"evapotranspiration":16.0,"rainfall":1.8,"year":8,"week":36},{"evapotranspiration":14.7,"rainfall":22.467,"year":9,"week":36},{"evapotranspiration":13.0,"rainfall":69.133,"year":10,"week":36},{"evapotranspiration":14.5,"rainfall":3.533,"year":11,"week":36},{"evapotranspiration":12.8,"rainfall":15.167,"year":12,"week":36},{"evapotranspiration":17.1,"rainfall":0.333,"year":13,"week":36},{"evapotranspiration":15.6,"rainfall":20.733,"year":14,"week":36},{"evapotranspiration":13.3,"rainfall":0.333,"year":15,"week":36},{"evapotranspiration":13.8,"rainfall":13.7,"year":16,"week":36},{"evapotranspiration":19.6,"rainfall":8.067,"year":17,"week":36},{"evapotranspiration":18.0,"rainfall":18.533,"year":18,"week":36},{"evapotranspiration":13.4,"rainfall":10.2,"year":19,"week":36},{"evapotranspiration":13.3,"rainfall":229.2,"year":20,"week":36}],[{"evapotranspiration":13.2,"rainfall":39.767,"year":1,"week":37},{"evapotranspiration":12.1,"rainfall":50.133,"year":2,"week":37},{"evapotranspiration":11.3,"rainfall":25.433,"year":3,"week":37},{"evapotranspiration":11.0,"rainfall":117.367,"year":4,"week":37},{"evapotranspiration":12.1,"rainfall":182.4,"year":5,"week":37},{"evapotranspiration":13.9,"rainfall":2.033,"year":6,"week":37},{"evapotranspiration":12.1,"rainfall":68.833,"year":7,"week":37},{"evapotranspiration":12.6,"rainfall":1.933,"year":8,"week":37},{"evapotranspiration":14.0,"rainfall":0.2,"year":9,"week":37},{"evapotranspiration":12.0,"rainfall":18.7,"year":10,"week":37},{"evapotranspiration":13.0,"rainfall":6.467,"year":11,"week":37},{"evapotranspiration":13.5,"rainfall":13.533,"year":12,"week":37},{"evapotranspiration":13.6,"rainfall":7.533,"year":13,"week":37},{"evapotranspiration":12.4,"rainfall":34.233,"year":14,"week":37},{"evapotranspiration":15.4,"rainfall":34.8,"year":15,"week":37},{"evapotranspiration":14.7,"rainfall":0.733,"year":16,"week":37},{"evapotranspiration":12.0,"rainfall":101.4,"year":17,"week":37},{"evapotranspiration":13.2,"rainfall":25.733,"year":18,"week":37},{"evapotranspiration":11.9,"rainfall":5.7,"year":19,"week":37},{"evapotranspiration":10.6,"rainfall":193.0,"year":20,"week":37}],[{"evapotranspiration":9.8,"rainfall":25.633,"year":1,"week":38},{"evapotranspiration":12.7,"rainfall":8.267,"year":2,"week":38},{"evapotranspiration":10.1,"rainfall":6.2,"year":3,"week":38},{"evapotranspiration":10.4,"rainfall":81.433,"year":4,"week":38},{"evapotranspiration":9.6,"rainfall":3.667,"year":5,"week":38},{"evapotranspiration":11.9,"rainfall":0.067,"year":6,"week":38},{"evapotranspiration":12.7,"rainfall":19.033,"year":7,"week":38},{"evapotranspiration":11.2,"rainfall":0.333,"year":8,"week":38},{"evapotranspiration":9.8,"rainfall":2.333,"year":9,"week":38},{"evapotranspiration":9.6,"rainfall":32.2,"year":10,"week":38},{"evapotranspiration":10.8,"rainfall":5.333,"year":11,"week":38},{"evapotranspiration":8.2,"rainfall":170.967,"year":12,"week":38},{"evapotranspiration":12.6,"rainfall":0.133,"year":13,"week":38},{"evapotranspiration":9.2,"rainfall":13.767,"year":14,"week":38},{"evapotranspiration":12.4,"rainfall":0.0,"year":15,"week":38},{"evapotranspiration":8.3,"rainfall":228.5,"year":16,"week":38},{"evapotranspiration":8.3,"rainfall":126.233,"year":17,"week":38},{"evapotranspiration":9.0,"rainfall":90.0,"year":18,"week":38},{"evapotranspiration":10.2,"rainfall":74.533,"year":19,"week":38},{"evapotranspiration":13.0,"rainfall":12.933,"year":20,"week":38}],[{"evapotranspiration":8.5,"rainfall":7.6,"year":1,"week":39},{"evapotranspiration":7.2,"rainfall":59.1,"year":2,"week":39},{"evapotranspiration":5.7,"rainfall":115.9,"year":3,"week":39},{"evapotranspiration":8.3,"rainfall":22.1,"year":4,"week":39},{"evapotranspiration":9.8,"rainfall":4.333,"year":5,"week":39},{"evapotranspiration":7.9,"rainfall":98.467,"year":6,"week":39},{"evapotranspiration":9.2,"rainfall":59.2,"year":7,"week":39},{"evapotranspiration":10.1,"rainfall":1.067,"year":8,"week":39},{"evapotranspiration":8.5,"rainfall":2.167,"year":9,"week":39},{"evapotranspiration":8.1,"rainfall":142.3,"year":10,"week":39},{"evapotranspiration":9.0,"rainfall":45.667,"year":11,"week":39},{"evapotranspiration":6.6,"rainfall":18.867,"year":12,"week":39},{"evapotranspiration":6.0,"rainfall":78.733,"year":13,"week":39},{"evapotranspiration":6.1,"rainfall":133.633,"year":14,"week":39},{"evapotranspiration":9.6,"rainfall":25.867,"year":15,"week":39},{"evapotranspiration":9.5,"rainfall":22.667,"year":16,"week":39},{"evapotranspiration":10.6,"rainfall":6.833,"year":17,"week":39},{"evapotranspiration":10.8,"rainfall":9.867,"year":18,"week":39},{"evapotranspiration":8.7,"rainfall":0.267,"year":19,"week":39},{"evapotranspiration":9.4,"rainfall":18.467,"year":20,"week":39}],[{"evapotranspiration":8.5,"rainfall":0.4,"year":1,"week":40},{"evapotranspiration":8.5,"rainfall":10.1,"year":2,"week":40},{"evapotranspiration":5.6,"rainfall":0.933,"year":3,"week":40},{"evapotranspiration":7.6,"rainfall":0.2,"year":4,"week":40},{"evapotranspiration":6.4,"rainfall":169.167,"year":5,"week":40},{"evapotranspiration":8.4,"rainfall":7.133,"year":6,"week":40},{"evapotranspiration":6.9,"rainfall":28.767,"year":7,"week":40},{"evapotranspiration":5.0,"rainfall":274.5,"year":8,"week":40},{"evapotranspiration":6.5,"rainfall":111.4,"year":9,"week":40},{"evapotranspiration":7.5,"rainfall":49.533,"year":10,"week":40},{"evapotranspiration":7.9,"rainfall":73.333,"year":11,"week":40},{"evapotranspiration":6.7,"rainfall":119.5,"year":12,"week":40},{"evapotranspiration":7.7,"rainfall":39.633,"year":13,"week":40},{"evapotranspiration":7.6,"rainfall":106.833,"year":14,"week":40},{"evapotranspiration":7.3,"rainfall":0.0,"year":15,"week":40},{"evapotranspiration":9.3,"rainfall":33.967,"year":16,"week":40},{"evapotranspiration":9.4,"rainfall":14.567,"year":17,"week":40},{"evapotranspiration":7.5,"rainfall":44.8,"year":18,"week":40},{"evapotranspiration":8.1,"rainfall":4.4,"year":19,"week":40},{"evapotranspiration":8.4,"rainfall":8.0,"year":20,"week":40}],[{"evapotranspiration":6.8,"rainfall":0.2,"year":1,"week":41},{"evapotranspiration":5.6,"rainfall":55.967,"year":2,"week":41},{"evapotranspiration":5.0,"rainfall":14.4,"year":3,"week":41},{"evapotranspiration":4.1,"rainfall":70.733,"year":4,"week":41},{"evapotranspiration":6.8,"rainfall":70.8,"year":5,"week":41},{"evapotranspiration":6.2,"rainfall":1.167,"year":6,"week":41},{"evapotranspiration":6.6,"rainfall":0.467,"year":7,"week":41},{"evapotranspiration":7.0,"rainfall":22.233,"year":8,"week":41},{"evapotranspiration":5.6,"rainfall":1.267,"year":9,"week":41},{"evapotranspiration":5.1,"rainfall":19.9,"year":10,"week":41},{"evapotranspiration":6.7,"rainfall":1.833,"year":11,"week":41},{"evapotranspiration":4.5,"rainfall":129.033,"year":12,"week":41},{"evapotranspiration":5.7,"rainfall":20.533,"year":13,"week":41},{"evapotranspiration":6.8,"rainfall":37.5,"year":14,"week":41},{"evapotranspiration":6.6,"rainfall":79.933,"year":15,"week":41},{"evapotranspiration":5.5,"rainfall":51.3,"year":16,"week":41},{"evapotranspiration":7.4,"rainfall":24.0,"year":17,"week":41},{"evapotranspiration":6.9,"rainfall":31.5,"year":18,"week":41},{"evapotranspiration":6.3,"rainfall":8.133,"year":19,"week":41},{"evapotranspiration":5.5,"rainfall":79.733,"year":20,"week":41}],[{"evapotranspiration":3.7,"rainfall":15.6,"year":1,"week":42},{"evapotranspiration":4.0,"rainfall":10.533,"year":2,"week":42},{"evapotranspiration":4.5,"rainfall":18.7,"year":3,"week":42},{"evapotranspiration":4.3,"rainfall":12.667,"year":4,"week":42},{"evapotranspiration":5.0,"rainfall":5.2,"year":5,"week":42},{"evapotranspiration":3.9,"rainfall":0.733,"year":6,"week":42},{"evapotranspiration":5.2,"rainfall":9.4,"year":7,"week":42},{"evapotranspiration":4.7,"rainfall":110.967,"year":8,"week":42},{"evapotranspiration":3.0,"rainfall":309.933,"year":9,"week":42},{"evapotranspiration":4.1,"rainfall":9.533,"year":10,"week":42},{"evapotranspiration":5.3,"rainfall":2.5,"year":11,"week":42},{"evapotranspiration":5.3,"rainfall":1.333,"year":12,"week":42},{"evapotranspiration":4.6,"rainfall":39.2,"year":13,"week":42},{"evapotranspiration":4.9,"rainfall":7.467,"year":14,"week":42},{"evapotranspiration":4.2,"rainfall":30.433,"year":15,"week":42},{"evapotranspiration":5.2,"rainfall":37.967,"year":16,"week":42},{"evapotranspiration":6.0,"rainfall":10.867,"year":17,"week":42},{"evapotranspiration":5.3,"rainfall":31.667,"year":18,"week":42},{"evapotranspiration":4.7,"rainfall":38.467,"year":19,"week":42},{"evapotranspiration":4.1,"rainfall":34.6,"year":20,"week":42}],[{"evapotranspiration":3.1,"rainfall":134.0,"year":1,"week":43},{"evapotranspiration":3.8,"rainfall":51.4,"year":2,"week":43},{"evapotranspiration":3.4,"rainfall":0.767,"year":3,"week":43},{"evapotranspiration":3.8,"rainfall":1.4,"year":4,"week":43},{"evapotranspiration":3.1,"rainfall":20.367,"year":5,"week":43},{"evapotranspiration":2.9,"rainfall":53.267,"year":6,"week":43},{"evapotranspiration":3.5,"rainfall":71.367,"year":7,"week":43},{"evapotranspiration":3.9,"rainfall":37.8,"year":8,"week":43},{"evapotranspiration":3.6,"rainfall":54.4,"year":9,"week":43},{"evapotranspiration":3.1,"rainfall":102.967,"year":10,"week":43},{"evapotranspiration":3.7,"rainfall":26.4,"year":11,"week":43},{"evapotranspiration":3.5,"rainfall":3.567,"year":12,"week":43},{"evapotranspiration":3.5,"rainfall":12.5,"year":13,"week":43},{"evapotranspiration":4.4,"rainfall":87.167,"year":14,"week":43},{"evapotranspiration":3.8,"rainfall":23.333,"year":15,"week":43},{"evapotranspiration":3.8,"rainfall":58.533,"year":16,"week":43},{"evapotranspiration":4.8,"rainfall":18.667,"year":17,"week":43},{"evapotranspiration":4.0,"rainfall":48.2,"year":18,"week":43},{"evapotranspiration":3.1,"rainfall":46.033,"year":19,"week":43},{"evapotranspiration":2.8,"rainfall":70.1,"year":20,"week":43}],[{"evapotranspiration":2.8,"rainfall":31.8,"year":1,"week":44},{"evapotranspiration":3.5,"rainfall":11.233,"year":2,"week":44},{"evapotranspiration":2.0,"rainfall":62.133,"year":3,"week":44},{"evapotranspiration":2.0,"rainfall":104.2,"year":4,"week":44},{"evapotranspiration":1.7,"rainfall":26.733,"year":5,"week":44},{"evapotranspiration":2.7,"rainfall":45.9,"year":6,"week":44},{"evapotranspiration":3.5,"rainfall":0.833,"year":7,"week":44},{"evapotranspiration":2.9,"rainfall":66.867,"year":8,"week":44},{"evapotranspiration":2.5,"rainfall":68.133,"year":9,"week":44},{"evapotranspiration":3.1,"rainfall":33.8,"year":10,"week":44},{"evapotranspiration":3.0,"rainfall":5.6,"year":11,"week":44},{"evapotranspiration":2.7,"rainfall":0.467,"year":12,"week":44},{"evapotranspiration":2.4,"rainfall":19.267,"year":13,"week":44},{"evapotranspiration":2.6,"rainfall":28.233,"year":14,"week":44},{"evapotranspiration":2.9,"rainfall":14.3,"year":15,"week":44},{"evapotranspiration":3.3,"rainfall":10.4,"year":16,"week":44},{"evapotranspiration":2.7,"rainfall":15.567,"year":17,"week":44},{"evapotranspiration":2.9,"rainfall":3.967,"year":18,"week":44},{"evapotranspiration":2.4,"rainfall":33.067,"year":19,"week":44},{"evapotranspiration":3.6,"rainfall":6.467,"year":20,"week":44}],[{"evapotranspiration":1.6,"rainfall":86.083,"year":1,"week":45},{"evapotranspiration":2.3,"rainfall":16.367,"year":2,"week":45},{"evapotranspiration":2.1,"rainfall":32.533,"year":3,"week":45},{"evapotranspiration":1.6,"rainfall":15.4,"year":4,"week":45},{"evapotranspiration":1.7,"rainfall":2.067,"year":5,"week":45},{"evapotranspiration":2.2,"rainfall":3.633,"year":6,"week":45},{"evapotranspiration":2.9,"rainfall":23.533,"year":7,"week":45},{"evapotranspiration":1.9,"rainfall":26.033,"year":8,"week":45},{"evapotranspiration":1.8,"rainfall":4.833,"year":9,"week":45},{"evapotranspiration":2.0,"rainfall":10.8,"year":10,"week":45},{"evapotranspiration":2.4,"rainfall":15.333,"year":11,"week":45},{"evapotranspiration":2.5,"rainfall":10.8,"year":12,"week":45},{"evapotranspiration":1.8,"rainfall":0.0,"year":13,"week":45},{"evapotranspiration":2.7,"rainfall":84.6,"year":14,"week":45},{"evapotranspiration":2.5,"rainfall":27.333,"year":15,"week":45},{"evapotranspiration":1.8,"rainfall":52.0,"year":16,"week":45},{"evapotranspiration":2.6,"rainfall":13.967,"year":17,"week":45},{"evapotranspiration":2.6,"rainfall":82.0,"year":18,"week":45},{"evapotranspiration":2.3,"rainfall":35.367,"year":19,"week":45},{"evapotranspiration":2.3,"rainfall":5.8,"year":20,"week":45}],[{"evapotranspiration":1.7,"rainfall":29.267,"year":1,"week":46},{"evapotranspiration":1.7,"rainfall":127.1,"year":2,"week":46},{"evapotranspiration":2.1,"rainfall":38.733,"year":3,"week":46},{"evapotranspiration":1.4,"rainfall":2.4,"year":4,"week":46},{"evapotranspiration":1.2,"rainfall":42.367,"year":5,"week":46},{"evapotranspiration":1.9,"rainfall":35.733,"year":6,"week":46},{"evapotranspiration":2.1,"rainfall":37.933,"year":7,"week":46},{"evapotranspiration":1.5,"rainfall":17.433,"year":8,"week":46},{"evapotranspiration":1.1,"rainfall":48.2,"year":9,"week":46},{"evapotranspiration":1.6,"rainfall":36.433,"year":10,"week":46},{"evapotranspiration":1.7,"rainfall":17.8,"year":11,"week":46},{"evapotranspiration":1.7,"rainfall":2.733,"year":12,"week":46},{"evapotranspiration":1.4,"rainfall":173.4,"year":13,"week":46},{"evapotranspiration":2.1,"rainfall":26.1,"year":14,"week":46},{"evapotranspiration":1.3,"rainfall":0.0,"year":15,"week":46},{"evapotranspiration":2.1,"rainfall":83.267,"year":16,"week":46},{"evapotranspiration":1.5,"rainfall":234.333,"year":17,"week":46},{"evapotranspiration":2.0,"rainfall":3.633,"year":18,"week":46},{"evapotranspiration":2.0,"rainfall":4.6,"year":19,"week":46},{"evapotranspiration":2.0,"rainfall":31.533,"year":20,"week":46}],[{"evapotranspiration":1.7,"rainfall":52.5,"year":1,"week":47},{"evapotranspiration":1.3,"rainfall":36.233,"year":2,"week":47},{"evapotranspiration":1.0,"rainfall":1.2,"year":3,"week":47},{"evapotranspiration":1.8,"rainfall":9.733,"year":4,"week":47},{"evapotranspiration":1.7,"rainfall":7.967,"year":5,"week":47},{"evapotranspiration":1.3,"rainfall":67.5,"year":6,"week":47},{"evapotranspiration":2.1,"rainfall":53.933,"year":7,"week":47},{"evapotranspiration":1.7,"rainfall":74.6,"year":8,"week":47},{"evapotranspiration":1.5,"rainfall":90.3,"year":9,"week":47},{"evapotranspiration":1.0,"rainfall":14.767,"year":10,"week":47},{"evapotranspiration":1.3,"rainfall":48.8,"year":11,"week":47},{"evapotranspiration":1.2,"rainfall":117.733,"year":12,"week":47},{"evapotranspiration":1.3,"rainfall":4.1,"year":13,"week":47},{"evapotranspiration":2.0,"rainfall":37.0,"year":14,"week":47},{"evapotranspiration":1.9,"rainfall":35.667,"year":15,"week":47},{"evapotranspiration":1.9,"rainfall":77.167,"year":16,"week":47},{"evapotranspiration":2.0,"rainfall":20.467,"year":17,"week":47},{"evapotranspiration":1.2,"rainfall":24.533,"year":18,"week":47},{"evapotranspiration":1.2,"rainfall":133.933,"year":19,"week":47},{"evapotranspiration":1.9,"rainfall":75.65,"year":20,"week":47}],[{"evapotranspiration":1.3,"rainfall":3.633,"year":1,"week":48},{"evapotranspiration":1.6,"rainfall":27.767,"year":2,"week":48},{"evapotranspiration":1.0,"rainfall":17.267,"year":3,"week":48},{"evapotranspiration":1.6,"rainfall":83.9,"year":4,"week":48},{"evapotranspiration":1.8,"rainfall":17.567,"year":5,"week":48},{"evapotranspiration":2.1,"rainfall":50.2,"year":6,"week":48},{"evapotranspiration":1.1,"rainfall":26.233,"year":7,"week":48},{"evapotranspiration":1.6,"rainfall":19.033,"year":8,"week":48},{"evapotranspiration":1.0,"rainfall":0.0,"year":9,"week":48},{"evapotranspiration":1.2,"rainfall":0.0,"year":10,"week":48},{"evapotranspiration":0.9,"rainfall":92.4,"year":11,"week":48},{"evapotranspiration":1.0,"rainfall":123.1,"year":12,"week":48},{"evapotranspiration":0.8,"rainfall":20.667,"year":13,"week":48},{"evapotranspiration":1.6,"rainfall":8.733,"year":14,"week":48},{"evapotranspiration":1.8,"rainfall":22.8,"year":15,"week":48},{"evapotranspiration":1.1,"rainfall":2.0,"year":16,"week":48},{"evapotranspiration":1.7,"rainfall":61.533,"year":17,"week":48},{"evapotranspiration":1.7,"rainfall":4.333,"year":18,"week":48},{"evapotranspiration":2.0,"rainfall":86.133,"year":19,"week":48},{"evapotranspiration":1.8,"rainfall":42.133,"year":20,"week":48}],[{"evapotranspiration":1.4,"rainfall":95.7,"year":1,"week":49},{"evapotranspiration":1.3,"rainfall":84.533,"year":2,"week":49},{"evapotranspiration":1.9,"rainfall":11.067,"year":3,"week":49},{"evapotranspiration":1.3,"rainfall":10.4,"year":4,"week":49},{"evapotranspiration":0.9,"rainfall":0.0,"year":5,"week":49},{"evapotranspiration":1.6,"rainfall":80.667,"year":6,"week":49},{"evapotranspiration":1.7,"rainfall":33.567,"year":7,"week":49},{"evapotranspiration":1.2,"rainfall":48.8,"year":8,"week":49},{"evapotranspiration":1.8,"rainfall":73.833,"year":9,"week":49},{"evapotranspiration":1.7,"rainfall":22.1,"year":10,"week":49},{"evapotranspiration":1.8,"rainfall":73.55,"year":11,"week":49},{"evapotranspiration":1.5,"rainfall":20.567,"year":12,"week":49},{"evapotranspiration":1.0,"rainfall":102.9,"year":13,"week":49},{"evapotranspiration":1.9,"rainfall":47.067,"year":14,"week":49},{"evapotranspiration":1.7,"rainfall":99.133,"year":15,"week":49},{"evapotranspiration":2.5,"rainfall":6.867,"year":16,"week":49},{"evapotranspiration":1.7,"rainfall":35.167,"year":17,"week":49},{"evapotranspiration":2.0,"rainfall":13.467,"year":18,"week":49},{"evapotranspiration":1.7,"rainfall":43.4,"year":19,"week":49},{"evapotranspiration":1.9,"rainfall":126.333,"year":20,"week":49}],[{"evapotranspiration":1.9,"rainfall":22.767,"year":1,"week":50},{"evapotranspiration":1.3,"rainfall":174.433,"year":2,"week":50},{"evapotranspiration":2.0,"rainfall":163.367,"year":3,"week":50},{"evapotranspiration":1.7,"rainfall":10.833,"year":4,"week":50},{"evapotranspiration":1.3,"rainfall":2.9,"year":5,"week":50},{"evapotranspiration":1.9,"rainfall":50.733,"year":6,"week":50},{"evapotranspiration":1.3,"rainfall":4.667,"year":7,"week":50},{"evapotranspiration":1.8,"rainfall":23.867,"year":8,"week":50},{"evapotranspiration":2.3,"rainfall":120.1,"year":9,"week":50},{"evapotranspiration":2.5,"rainfall":17.067,"year":10,"week":50},{"evapotranspiration":1.4,"rainfall":19.4,"year":11,"week":50},{"evapotranspiration":1.3,"rainfall":31.233,"year":12,"week":50},{"evapotranspiration":1.5,"rainfall":51.467,"year":13,"week":50},{"evapotranspiration":2.4,"rainfall":58.533,"year":14,"week":50},{"evapotranspiration":2.1,"rainfall":0.6,"year":15,"week":50},{"evapotranspiration":2.0,"rainfall":40.733,"year":16,"week":50},{"evapotranspiration":1.6,"rainfall":106.2,"year":17,"week":50},{"evapotranspiration":1.9,"rainfall":25.433,"year":18,"week":50},{"evapotranspiration":2.5,"rainfall":56.333,"year":19,"week":50},{"evapotranspiration":2.2,"rainfall":21.967,"year":20,"week":50}],[{"evapotranspiration":1.8,"rainfall":10.967,"year":1,"week":51},{"evapotranspiration":2.2,"rainfall":133.767,"year":2,"week":51},{"evapotranspiration":2.8,"rainfall":56.333,"year":3,"week":51},{"evapotranspiration":2.3,"rainfall":103.5,"year":4,"week":51},{"evapotranspiration":2.4,"rainfall":45.767,"year":5,"week":51},{"evapotranspiration":2.5,"rainfall":0.0,"year":6,"week":51},{"evapotranspiration":1.9,"rainfall":4.3,"year":7,"week":51},{"evapotranspiration":1.6,"rainfall":105.867,"year":8,"week":51},{"evapotranspiration":2.4,"rainfall":29.167,"year":9,"week":51},{"evapotranspiration":2.3,"rainfall":75.067,"year":10,"week":51},{"evapotranspiration":2.2,"rainfall":110.9,"year":11,"week":51},{"evapotranspiration":2.1,"rainfall":58.4,"year":12,"week":51},{"evapotranspiration":1.4,"rainfall":65.567,"year":13,"week":51},{"evapotranspiration":1.6,"rainfall":52.133,"year":14,"week":51},{"evapotranspiration":2.6,"rainfall":21.567,"year":15,"week":51},{"evapotranspiration":2.5,"rainfall":73.933,"year":16,"week":51},{"evapotranspiration":2.2,"rainfall":4.433,"year":17,"week":51},{"evapotranspiration":2.8,"rainfall":3.283,"year":18,"week":51},{"evapotranspiration":1.8,"rainfall":60.133,"year":19,"week":51},{"evapotranspiration":3.3,"rainfall":62.967,"year":20,"week":51}],[{"evapotranspiration":3.5,"rainfall":0.6,"year":1,"week":52},{"evapotranspiration":2.1,"rainfall":33.967,"year":2,"week":52},{"evapotranspiration":3.4,"rainfall":9.733,"year":3,"week":52},{"evapotranspiration":3.2,"rainfall":39.633,"year":4,"week":52},{"evapotranspiration":2.9,"rainfall":0.233,"year":5,"week":52},{"evapotranspiration":3.3,"rainfall":45.067,"year":6,"week":52},{"evapotranspiration":3.0,"rainfall":0.0,"year":7,"week":52},{"evapotranspiration":2.5,"rainfall":11.9,"year":8,"week":52},{"evapotranspiration":3.9,"rainfall":16.333,"year":9,"week":52},{"evapotranspiration":3.6,"rainfall":0.0,"year":10,"week":52},{"evapotranspiration":3.2,"rainfall":1.3,"year":11,"week":52},{"evapotranspiration":2.5,"rainfall":97.033,"year":12,"week":52},{"evapotranspiration":3.2,"rainfall":25.567,"year":13,"week":52},{"evapotranspiration":4.2,"rainfall":9.767,"year":14,"week":52},{"evapotranspiration":3.6,"rainfall":14.933,"year":15,"week":52},{"evapotranspiration":3.0,"rainfall":167.333,"year":16,"week":52},{"evapotranspiration":3.3,"rainfall":1.7,"year":17,"week":52},{"evapotranspiration":3.2,"rainfall":13.967,"year":18,"week":52},{"evapotranspiration":3.0,"rainfall":13.8,"year":19,"week":52},{"evapotranspiration":3.1,"rainfall":75.833,"year":20,"week":52}]],"maximum_irrigation":0.0,"energy_content_of_milk":[78.42618181669921,79.79011205800985,80.87709384097045,81.69314742025884,82.26941235352766,82.64814789569853,82.87246731524012,82.98064707378965,83.00397275799544,82.966688495664,82.88692243889552,82.77790173190063,82.6491140473981,82.50728247224228,82.35712860922682,82.20194543608156,82.04401606959651,81.88491458644674,81.72571960491835,81.567164727611,81.40974393583333,81.25378514888264,81.09950143093988,80.94702657273103,80.79643978337313,80.64778280832743,80.50107178711492,80.35630546120294,80.21347085113005,80.07254717963588,79.93350857956332,79.7963259600397,79.6609682897911,79.52740347695058,79.39559896962324,79.26552216329229,79.13714067469846,79.01042252349748,78.88533625030595,78.76185099094812,78.63993652062312,78.51956327748961,78.4007023722394,78.28332558820448,78.16740537513867,78.05291483884001,77.93982772810837,77.82811842006423,77.7177619045319,77.60873376796641,77.5010101772496,77.39456786357167],"fixed_cost":3536,"initial_storage":0.0,"number_of_weeks":52,"cost_irrigation":0.5,"harvesting_efficiency":0.9,"number_cuts":500,"energy_for_pregnancy":[0.0,0.0,0.0,0.0,0.0,0.0,0.0,0.0,0.0,0.0,0.0,0.46942084128448225,1.7981421893994396,2.0667638260904315,2.37551442706686,2.730388795258448,3.138277287786411,3.6070996013971657,4.145958543891779,4.765316777227694,5.47719996399474,6.295430261624043,7.235894697929969,8.316853638852654,9.559295337711962,10.987343450017464,12.628725426275688,14.515310877262927,16.683730364840375,19.176086632956984,22.040772088334446,25.333408403307374,29.117926484455666,33.467807776054094,38.46751099989413,44.21411203352622,50.819188767336385,58.410987537460166,67.1369131987062,77.16639118556151,88.69415713199427,101.94403792239028,117.17329758774918,134.6776324284851,154.79691235077559,177.92177989212678,204.50123506500168,235.0513532883204,270.1653056770518,310.5248762471245,356.9136996574853,410.2324765176468],"random_seed":1234,"yearly_pasture_growth":14000.0,"final_pasture_cover":2500.0,"objective_bound":1.0e6,"initial_pasture_cover":2500.0,"energy_for_maintenance":378.0,"maximum_milk_production":10000,"first_week":31,"stocking_rate":3.0,"soil_fertility":[37.299452293384526,30.159967194416783,25.944808724142078,25.14151964420359,22.683956850840936,23.735572728986877,22.012247390978647,21.859635274910744,22.512796559902913,21.36909721022941,23.636810373475086,19.08865792980886,17.030709051887055,15.129792338064721,14.142595205213967,12.685183698244767,11.740761344746971,10.379298522580708,10.422577867295242,9.064162667151441,8.165587620521373,8.259701472540351,7.984068811720197,8.18510070261968,8.241377562835174,8.739092129375022,8.957967701087638,9.88937644948754,11.209745161802218,10.317992634236415,11.050304757905051,11.602329416232804,11.610204138487298,12.812154353759233,13.453722477982355,16.041774594679545,17.720331209536365,20.455283395564923,24.006135535560635,25.53954056546848,30.08521000591724,37.0783367190845,43.03198566785081,49.83647408479098,55.524233145477226,61.31201644589886,67.44321809048876,72.84807528937809,64.33045417862003,56.659614113960735,52.005662169541495,39.87694140892918],"harvest_cost":0.275,"max_milk_energy":[888.195937634907,1049.1514487251575,1119.2251879670555,1145.8199482062532,1153.1425876680617,1151.9399911037517,1146.9832305720242,1140.390302597011,1133.10132124619,1125.5334584687225,1117.8717174491046,1110.1980270217546,1102.5485556100919,1094.9391568425867,1087.3766666137458,1079.8639186219375,1072.4019711042286,1064.9910954285422,1057.6312149886248,1050.3221000504295,1043.0634542485054,1035.8549529783854,1028.696260432342,1021.58703715352,1014.5269433805836,1007.5156405235441,1000.5527918099543,993.6380625628293,986.7711203151335,979.9516348517623,973.179278219401,966.453724722179,959.7746509110793,953.1417355706363,946.5546597044857,940.0131065204682,933.5167614155914,927.0653119609857,920.6584478869191,914.2958610678918,907.9772455078248,901.702297325348,895.4707147391865,889.2821980536476,883.1364496442081,877.0331739432014,870.9720774256009,864.9528685949056,858.9752579691203,853.0389580668332,847.1436833933905,841.2891504271661],"maximum_pasture_cover":3500.0,"initial_soil_moisture":150.0,"energy_for_bcs_dry":[-72.33436602213311,-67.68903976383099,-63.04371350552886,-58.39838724722673,-53.7530609889246,-49.10773473062248,-44.462408472320355,-39.81708221401823,-35.1717559557161,-30.52642969741398,-25.88110343911185,-21.23577718080972,-16.5904509225076,-11.945124664205467,-7.29979840590334,-2.6544721476012154,7.103734772107579,9.84913951495109,11.530699919942737,13.212260324934384,14.893820729926036,16.575381134917684,18.256941539909334,19.93850194490098,21.620062349892628,23.301622754884285,24.983183159875928,26.664743564867578,28.346303969859232,30.02786437485088,31.70942477984253,33.39098518483417,35.07254558982582,36.75410599481748,38.43566639980912,40.11722680480078,41.79878720979242,43.48034761478407,45.16190801977572,46.84346842476737,48.52502882975902,50.20658923475068,51.888149639742316,53.56971004473396,55.25127044972562,56.932830854717274,58.61439125970892,60.29595166470057,61.97751206969221,63.65907247468386,65.34063287967551,67.02219328466717],"supplement_energy_density":11.0,"maximum_lactation":44,"number_of_pasture_cuts":20,"min_milk_production":6.3,"energy_correction_factor":1.1}